{ "Name": "Deck_Plate_1(Clone)", "Transform": { "PX": 46.77698,"PY": 0.0002724126,"PZ": -76.55859,"RX": 0,"RY": 256.5,"RZ": 0,"SX": 0.05,"SY": 0.05,"SZ": 0.05}, "Children": [{ "Name": "Plating", "Transform": { "PX": 0,"PY": 0,"PZ": 0,"RX": -4.32571E-06,"RY": -5.088888E-14,"RZ": 1.921001E-21,"SX": 1,"SY": 1,"SZ": 1}, "Children": [] },{ "Name": "Rivets", "Transform": { "PX": 0,"PY": 0,"PZ": 0,"RX": -4.325711E-06,"RY": 0,"RZ": 0,"SX": 1,"SY": 1,"SZ": 1}, "Children": [] },{ "Name": "Snapping Root", "Transform": { "PX": 1707.263,"PY": -0.005448251,"PZ": 552.2452,"RX": 0,"RY": 0,"RZ": 0,"SX": 19.99999,"SY": 20,"SZ": 19.99999}, "Children": [] },{ "Name": "Snapping Root", "Transform": { "PX": -0.5000055,"PY": 50,"PZ": 24.99998,"RX": 0,"RY": 0,"RZ": 0,"SX": 19.99999,"SY": 20,"SZ": 19.99999}, "Children": [] },{ "Name": "Snapping Root", "Transform": { "PX": -0.5000055,"PY": 50,"PZ": 24.99998,"RX": 0,"RY": 0,"RZ": 0,"SX": 19.99999,"SY": 20,"SZ": 19.99999}, "Children": [] },{ "Name": "Snapping Root", "Transform": { "PX": -0.5000055,"PY": 50,"PZ": 24.99998,"RX": 0,"RY": 0,"RZ": 0,"SX": 19.99999,"SY": 20,"SZ": 19.99999}, "Children": [] },{ "Name": "Snapping Root", "Transform": { "PX": -0.5000055,"PY": 50,"PZ": 24.99998,"RX": 0,"RY": 0,"RZ": 0,"SX": 19.99999,"SY": 20,"SZ": 19.99999}, "Children": [] },{ "Name": "Snapping Root", "Transform": { "PX": -0.5000055,"PY": 50,"PZ": 24.99998,"RX": 0,"RY": 0,"RZ": 0,"SX": 19.99999,"SY": 20,"SZ": 19.99999}, "Children": [] },{ "Name": "Snapping Root", "Transform": { "PX": -0.5000055,"PY": 50,"PZ": 24.99998,"RX": 0,"RY": 0,"RZ": 0,"SX": 19.99999,"SY": 20,"SZ": 19.99999}, "Children": [] },{ "Name": "NoSync Bounds as Collision", "Transform": { "PX": -1707.763,"PY": 25.00545,"PZ": -527.2454,"RX": 0,"RY": 0,"RZ": 0,"SX": 2.442596,"SY": 2.5,"SZ": 0.6322327}, "Children": [] }] }