{ "Name": "Deck_Plate_1(Clone)", "Transform": { "PX": 25.24176,"PY": 0.0002701406,"PZ": -89.26428,"RX": 0,"RY": 251.5,"RZ": 0,"SX": 0.05,"SY": 0.05,"SZ": 0.05}, "Children": [{ "Name": "Plating", "Transform": { "PX": 0,"PY": 0,"PZ": 0,"RX": -4.32571E-06,"RY": -5.088888E-14,"RZ": 1.921001E-21,"SX": 1,"SY": 1,"SZ": 1}, "Children": [] },{ "Name": "Rivets", "Transform": { "PX": 0,"PY": 0,"PZ": 0,"RX": -4.325711E-06,"RY": 0,"RZ": 0,"SX": 1,"SY": 1,"SZ": 1}, "Children": [] },{ "Name": "Snapping Root", "Transform": { "PX": 1853.215,"PY": -0.005402812,"PZ": -87.73254,"RX": 0,"RY": 0,"RZ": 0,"SX": 19.99999,"SY": 20,"SZ": 19.99999}, "Children": [] },{ "Name": "Snapping Root", "Transform": { "PX": -0.5000502,"PY": 50,"PZ": 25,"RX": 0,"RY": 0,"RZ": 0,"SX": 19.99999,"SY": 20,"SZ": 19.99999}, "Children": [] },{ "Name": "Snapping Root", "Transform": { "PX": -0.5000502,"PY": 50,"PZ": 25,"RX": 0,"RY": 0,"RZ": 0,"SX": 19.99999,"SY": 20,"SZ": 19.99999}, "Children": [] },{ "Name": "Snapping Root", "Transform": { "PX": -0.5000502,"PY": 50,"PZ": 25,"RX": 0,"RY": 0,"RZ": 0,"SX": 19.99999,"SY": 20,"SZ": 19.99999}, "Children": [] },{ "Name": "Snapping Root", "Transform": { "PX": -0.5000502,"PY": 50,"PZ": 25,"RX": 0,"RY": 0,"RZ": 0,"SX": 19.99999,"SY": 20,"SZ": 19.99999}, "Children": [] },{ "Name": "Snapping Root", "Transform": { "PX": -0.5000502,"PY": 50,"PZ": 25,"RX": 0,"RY": 0,"RZ": 0,"SX": 19.99999,"SY": 20,"SZ": 19.99999}, "Children": [] },{ "Name": "Snapping Root", "Transform": { "PX": -0.5000502,"PY": 50,"PZ": 25,"RX": 0,"RY": 0,"RZ": 0,"SX": 19.99999,"SY": 20,"SZ": 19.99999}, "Children": [] },{ "Name": "NoSync Bounds as Collision", "Transform": { "PX": -1853.716,"PY": 25.00541,"PZ": 112.7325,"RX": 0,"RY": 0,"RZ": 0,"SX": 2.386673,"SY": 2.5,"SZ": 0.840683}, "Children": [] }] }